[{"id": "740beef63bb690b887fc4e67eced2927", "sport_key": "soccer_mexico_ligamx", "sport_title": "Liga MX", "commence_time": "2023-08-19T01:05:00Z", "home_team": "Le\u00f3n", "away_team": "Mazatl\u00e1n FC", "bookmakers": [{"key": "betrivers", "title": "BetRivers", "last_update": "2023-08-15T19:24:10Z", "markets": [{"key": "h2h", "last_update": "2023-08-15T19:24:10Z", "outcomes": [{"name": "Le\u00f3n", "price": 1.34}, {"name": "Mazatl\u00e1n FC", "price": 7.5}, {"name": "Draw", "price": 5.1}]}]}, {"key": "twinspires", "title": "TwinSpires", "last_update": "2023-08-15T19:24:44Z", "markets": [{"key": "h2h", "last_update": "2023-08-15T19:24:44Z", "outcomes": [{"name": "Le\u00f3n", "price": 1.34}, {"name": "Mazatl\u00e1n FC", "price": 7.5}, {"name": "Draw", "price": 5.1}]}]}, {"key": "betparx", "title": "betPARX", "last_update": "2023-08-15T19:25:11Z", "markets": [{"key": "h2h", "last_update": "2023-08-15T19:25:11Z", "outcomes": [{"name": "Le\u00f3n", "price": 1.34}, {"name": "Mazatl\u00e1n FC", "price": 7.5}, {"name": "Draw", "price": 5.1}]}]}, {"key": "tipico_us", "title": "Tipico", "last_update": "2023-08-15T19:24:44Z", "markets": [{"key": "h2h", "last_update": "2023-08-15T19:24:44Z", "outcomes": [{"name": "Le\u00f3n", "price": 1.37}, {"name": "Mazatl\u00e1n FC", "price": 7.5}, {"name": "Draw", "price": 4.9}]}]}, {"key": "unibet_us", "title": "Unibet", "last_update": "2023-08-15T19:23:51Z", "markets": [{"key": "h2h", "last_update": "2023-08-15T19:23:51Z", "outcomes": [{"name": "Le\u00f3n", "price": 1.34}, {"name": "Mazatl\u00e1n FC", "price": 7.5}, {"name": "Draw", "price": 5.1}]}]}, {"key": "superbook", "title": "SuperBook", "last_update": "2023-08-15T19:23:51Z", "markets": [{"key": "h2h", "last_update": "2023-08-15T19:23:51Z", "outcomes": [{"name": "Le\u00f3n", "price": 1.38}, {"name": "Mazatl\u00e1n FC", "price": 7.0}, {"name": "Draw", "price": 4.8}]}]}, {"key": "williamhill_us", "title": "William Hill (US)", "last_update": "2023-08-15T19:23:12Z", "markets": [{"key": "h2h", "last_update": "2023-08-15T19:23:12Z", "outcomes": [{"name": "Le\u00f3n", "price": 1.35}, {"name": "Mazatl\u00e1n FC", "price": 8.5}, {"name": "Draw", "price": 4.9}]}]}, {"key": "draftkings", "title": "DraftKings", "last_update": "2023-08-15T19:23:45Z", "markets": [{"key": "h2h", "last_update": "2023-08-15T19:23:45Z", "outcomes": [{"name": "Le\u00f3n", "price": 1.34}, {"name": "Mazatl\u00e1n FC", "price": 7.5}, {"name": "Draw", "price": 5.0}]}]}, {"key": "barstool", "title": "Barstool Sportsbook", "last_update": "2023-08-15T19:23:51Z", "markets": [{"key": "h2h", "last_update": "2023-08-15T19:23:51Z", "outcomes": [{"name": "Le\u00f3n", "price": 1.38}, {"name": "Mazatl\u00e1n FC", "price": 7.25}, {"name": "Draw", "price": 4.85}]}]}, {"key": "fanduel", "title": "FanDuel", "last_update": "2023-08-15T19:25:11Z", "markets": [{"key": "h2h", "last_update": "2023-08-15T19:25:11Z", "outcomes": [{"name": "Le\u00f3n", "price": 1.33}, {"name": "Mazatl\u00e1n FC", "price": 9.5}, {"name": "Draw", "price": 4.8}]}]}, {"key": "betonlineag", "title": "BetOnline.ag", "last_update": "2023-08-15T19:23:51Z", "markets": [{"key": "h2h", "last_update": "2023-08-15T19:23:51Z", "outcomes": [{"name": "Le\u00f3n", "price": 1.36}, {"name": "Mazatl\u00e1n FC", "price": 8.0}, {"name": "Draw", "price": 5.2}]}]}, {"key": "lowvig", "title": "LowVig.ag", "last_update": "2023-08-15T19:24:43Z", "markets": [{"key": "h2h", "last_update": "2023-08-15T19:24:43Z", "outcomes": [{"name": "Le\u00f3n", "price": 1.36}, {"name": "Mazatl\u00e1n FC", "price": 8.0}, {"name": "Draw", "price": 5.2}]}]}]}, {"id": "50dd3a4beb80c73889bfc96529f355b5", "sport_key": "soccer_mexico_ligamx", "sport_title": "Liga MX", "commence_time": "2023-08-19T03:00:00Z", "home_team": "Pumas", "away_team": "Toluca", "bookmakers": [{"key": "betrivers", "title": "BetRivers", "last_update": "2023-08-15T19:24:10Z", "markets": [{"key": "h2h", "last_update": "2023-08-15T19:24:10Z", "outcomes": [{"name": "Pumas", "price": 2.5}, {"name": "Toluca", "price": 2.55}, {"name": "Draw", "price": 3.45}]}]}, {"key": "twinspires", "title": "TwinSpires", "last_update": "2023-08-15T19:24:44Z", "markets": [{"key": "h2h", "last_update": "2023-08-15T19:24:44Z", "outcomes": [{"name": "Pumas", "price": 2.5}, {"name": "Toluca", "price": 2.55}, {"name": "Draw", "price": 3.45}]}]}, {"key": "betparx", "title": "betPARX", "last_update": "2023-08-15T19:25:11Z", "markets": [{"key": "h2h", "last_update": "2023-08-15T19:25:11Z", "outcomes": [{"name": "Pumas", "price": 2.5}, {"name": "Toluca", "price": 2.55}, {"name": "Draw", "price": 3.45}]}]}, {"key": "tipico_us", "title": "Tipico", "last_update": "2023-08-15T19:24:44Z", "markets": [{"key": "h2h", "last_update": "2023-08-15T19:24:44Z", "outcomes": [{"name": "Pumas", "price": 2.6}, {"name": "Toluca", "price": 2.65}, {"name": "Draw", "price": 3.4}]}]}, {"key": "unibet_us", "title": "Unibet", "last_update": "2023-08-15T19:23:51Z", "markets": [{"key": "h2h", "last_update": "2023-08-15T19:23:51Z", "outcomes": [{"name": "Pumas", "price": 2.5}, {"name": "Toluca", "price": 2.55}, {"name": "Draw", "price": 3.45}]}]}, {"key": "superbook", "title": "SuperBook", "last_update": "2023-08-15T19:23:51Z", "markets": [{"key": "h2h", "last_update": "2023-08-15T19:23:51Z", "outcomes": [{"name": "Pumas", "price": 2.6}, {"name": "Toluca", "price": 2.6}, {"name": "Draw", "price": 3.4}]}]}, {"key": "williamhill_us", "title": "William Hill (US)", "last_update": "2023-08-15T19:23:12Z", "markets": [{"key": "h2h", "last_update": "2023-08-15T19:23:12Z", "outcomes": [{"name": "Pumas", "price": 2.6}, {"name": "Toluca", "price": 2.55}, {"name": "Draw", "price": 3.55}]}]}, {"key": "draftkings", "title": "DraftKings", "last_update": "2023-08-15T19:23:45Z", "markets": [{"key": "h2h", "last_update": "2023-08-15T19:23:45Z", "outcomes": [{"name": "Pumas", "price": 2.55}, {"name": "Toluca", "price": 2.5}, {"name": "Draw", "price": 3.45}]}]}, {"key": "fanduel", "title": "FanDuel", "last_update": "2023-08-15T19:25:11Z", "markets": [{"key": "h2h", "last_update": "2023-08-15T19:25:11Z", "outcomes": [{"name": "Pumas", "price": 2.5}, {"name": "Toluca", "price": 2.6}, {"name": "Draw", "price": 3.4}]}]}, {"key": "barstool", "title": "Barstool Sportsbook", "last_update": "2023-08-15T19:23:51Z", "markets": [{"key": "h2h", "last_update": "2023-08-15T19:23:51Z", "outcomes": [{"name": "Pumas", "price": 2.57}, {"name": "Toluca", "price": 2.62}, {"name": "Draw", "price": 3.4}]}]}, {"key": "betonlineag", "title": "BetOnline.ag", "last_update": "2023-08-15T19:23:51Z", "markets": [{"key": "h2h", "last_update": "2023-08-15T19:23:51Z", "outcomes": [{"name": "Pumas", "price": 2.62}, {"name": "Toluca", "price": 2.57}, {"name": "Draw", "price": 3.58}]}]}, {"key": "lowvig", "title": "LowVig.ag", "last_update": "2023-08-15T19:24:43Z", "markets": [{"key": "h2h", "last_update": "2023-08-15T19:24:43Z", "outcomes": [{"name": "Pumas", "price": 2.62}, {"name": "Toluca", "price": 2.57}, {"name": "Draw", "price": 3.58}]}]}]}, {"id": "543b9eac7fe186df5ad3a6fdca02361b", "sport_key": "soccer_mexico_ligamx", "sport_title": "Liga MX", "commence_time": "2023-08-19T03:05:00Z", "home_team": "Puebla", "away_team": "Atl\u00e9tico San Luis", "bookmakers": [{"key": "betrivers", "title": "BetRivers", "last_update": "2023-08-15T19:24:10Z", "markets": [{"key": "h2h", "last_update": "2023-08-15T19:24:10Z", "outcomes": [{"name": "Atl\u00e9tico San Luis", "price": 2.95}, {"name": "Puebla", "price": 2.14}, {"name": "Draw", "price": 3.75}]}]}, {"key": "twinspires", "title": "TwinSpires", "last_update": "2023-08-15T19:24:44Z", "markets": [{"key": "h2h", "last_update": "2023-08-15T19:24:44Z", "outcomes": [{"name": "Atl\u00e9tico San Luis", "price": 2.95}, {"name": "Puebla", "price": 2.14}, {"name": "Draw", "price": 3.75}]}]}, {"key": "betparx", "title": "betPARX", "last_update": "2023-08-15T19:25:11Z", "markets": [{"key": "h2h", "last_update": "2023-08-15T19:25:11Z", "outcomes": [{"name": "Atl\u00e9tico San Luis", "price": 2.95}, {"name": "Puebla", "price": 2.14}, {"name": "Draw", "price": 3.75}]}]}, {"key": "tipico_us", "title": "Tipico", "last_update": "2023-08-15T19:24:44Z", "markets": [{"key": "h2h", "last_update": "2023-08-15T19:24:44Z", "outcomes": [{"name": "Atl\u00e9tico San Luis", "price": 3.05}, {"name": "Puebla", "price": 2.2}, {"name": "Draw", "price": 3.5}]}]}, {"key": "unibet_us", "title": "Unibet", "last_update": "2023-08-15T19:23:51Z", "markets": [{"key": "h2h", "last_update": "2023-08-15T19:23:51Z", "outcomes": [{"name": "Atl\u00e9tico San Luis", "price": 2.95}, {"name": "Puebla", "price": 2.14}, {"name": "Draw", "price": 3.75}]}]}, {"key": "superbook", "title": "SuperBook", "last_update": "2023-08-15T19:23:51Z", "markets": [{"key": "h2h", "last_update": "2023-08-15T19:23:51Z", "outcomes": [{"name": "Atl\u00e9tico San Luis", "price": 3.0}, {"name": "Puebla", "price": 2.2}, {"name": "Draw", "price": 3.45}]}]}, {"key": "williamhill_us", "title": "William Hill (US)", "last_update": "2023-08-15T19:23:12Z", "markets": [{"key": "h2h", "last_update": "2023-08-15T19:23:12Z", "outcomes": [{"name": "Atl\u00e9tico San Luis", "price": 3.05}, {"name": "Puebla", "price": 2.19}, {"name": "Draw", "price": 3.6}]}]}, {"key": "draftkings", "title": "DraftKings", "last_update": "2023-08-15T19:23:45Z", "markets": [{"key": "h2h", "last_update": "2023-08-15T19:23:45Z", "outcomes": [{"name": "Atl\u00e9tico San Luis", "price": 3.0}, {"name": "Puebla", "price": 2.15}, {"name": "Draw", "price": 3.6}]}]}, {"key": "fanduel", "title": "FanDuel", "last_update": "2023-08-15T19:25:11Z", "markets": [{"key": "h2h", "last_update": "2023-08-15T19:25:11Z", "outcomes": [{"name": "Atl\u00e9tico San Luis", "price": 3.0}, {"name": "Puebla", "price": 2.2}, {"name": "Draw", "price": 3.5}]}]}, {"key": "barstool", "title": "Barstool Sportsbook", "last_update": "2023-08-15T19:23:51Z", "markets": [{"key": "h2h", "last_update": "2023-08-15T19:23:51Z", "outcomes": [{"name": "Atl\u00e9tico San Luis", "price": 3.05}, {"name": "Puebla", "price": 2.18}, {"name": "Draw", "price": 3.5}]}]}, {"key": "betonlineag", "title": "BetOnline.ag", "last_update": "2023-08-15T19:23:51Z", "markets": [{"key": "h2h", "last_update": "2023-08-15T19:23:51Z", "outcomes": [{"name": "Atl\u00e9tico San Luis", "price": 3.1}, {"name": "Puebla", "price": 2.18}, {"name": "Draw", "price": 3.75}]}]}, {"key": "lowvig", "title": "LowVig.ag", "last_update": "2023-08-15T19:24:43Z", "markets": [{"key": "h2h", "last_update": "2023-08-15T19:24:43Z", "outcomes": [{"name": "Atl\u00e9tico San Luis", "price": 3.1}, {"name": "Puebla", "price": 2.18}, {"name": "Draw", "price": 3.75}]}]}]}, {"id": "f3713da80854a1f8ae96106032c3bc17", "sport_key": "soccer_mexico_ligamx", "sport_title": "Liga MX", "commence_time": "2023-08-19T03:10:00Z", "home_team": "FC Ju\u00e1rez", "away_team": "Guadalajara", "bookmakers": [{"key": "betrivers", "title": "BetRivers", "last_update": "2023-08-15T19:24:10Z", "markets": [{"key": "h2h", "last_update": "2023-08-15T19:24:10Z", "outcomes": [{"name": "FC Ju\u00e1rez", "price": 2.6}, {"name": "Guadalajara", "price": 2.8}, {"name": "Draw", "price": 3.0}]}]}, {"key": "twinspires", "title": "TwinSpires", "last_update": "2023-08-15T19:24:44Z", "markets": [{"key": "h2h", "last_update": "2023-08-15T19:24:44Z", "outcomes": [{"name": "FC Ju\u00e1rez", "price": 2.6}, {"name": "Guadalajara", "price": 2.8}, {"name": "Draw", "price": 3.0}]}]}, {"key": "betparx", "title": "betPARX", "last_update": "2023-08-15T19:25:11Z", "markets": [{"key": "h2h", "last_update": "2023-08-15T19:25:11Z", "outcomes": [{"name": "FC Ju\u00e1rez", "price": 2.6}, {"name": "Guadalajara", "price": 2.8}, {"name": "Draw", "price": 3.0}]}]}, {"key": "tipico_us", "title": "Tipico", "last_update": "2023-08-15T19:24:44Z", "markets": [{"key": "h2h", "last_update": "2023-08-15T19:24:44Z", "outcomes": [{"name": "FC Ju\u00e1rez", "price": 2.55}, {"name": "Guadalajara", "price": 2.7}, {"name": "Draw", "price": 3.15}]}]}, {"key": "unibet_us", "title": "Unibet", "last_update": "2023-08-15T19:23:51Z", "markets": [{"key": "h2h", "last_update": "2023-08-15T19:23:51Z", "outcomes": [{"name": "FC Ju\u00e1rez", "price": 2.6}, {"name": "Guadalajara", "price": 2.8}, {"name": "Draw", "price": 3.0}]}]}, {"key": "superbook", "title": "SuperBook", "last_update": "2023-08-15T19:23:51Z", "markets": [{"key": "h2h", "last_update": "2023-08-15T19:23:51Z", "outcomes": [{"name": "FC Ju\u00e1rez", "price": 2.65}, {"name": "Guadalajara", "price": 2.7}, {"name": "Draw", "price": 3.15}]}]}, {"key": "williamhill_us", "title": "William Hill (US)", "last_update": "2023-08-15T19:23:12Z", "markets": [{"key": "h2h", "last_update": "2023-08-15T19:23:12Z", "outcomes": [{"name": "FC Ju\u00e1rez", "price": 2.65}, {"name": "Guadalajara", "price": 2.75}, {"name": "Draw", "price": 3.1}]}]}, {"key": "draftkings", "title": "DraftKings", "last_update": "2023-08-15T19:23:45Z", "markets": [{"key": "h2h", "last_update": "2023-08-15T19:23:45Z", "outcomes": [{"name": "FC Ju\u00e1rez", "price": 2.6}, {"name": "Guadalajara", "price": 2.8}, {"name": "Draw", "price": 3.0}]}]}, {"key": "barstool", "title": "Barstool Sportsbook", "last_update": "2023-08-15T19:23:51Z", "markets": [{"key": "h2h", "last_update": "2023-08-15T19:23:51Z", "outcomes": [{"name": "FC Ju\u00e1rez", "price": 2.57}, {"name": "Guadalajara", "price": 2.7}, {"name": "Draw", "price": 3.15}]}]}, {"key": "betonlineag", "title": "BetOnline.ag", "last_update": "2023-08-15T19:23:51Z", "markets": [{"key": "h2h", "last_update": "2023-08-15T19:23:51Z", "outcomes": [{"name": "FC Ju\u00e1rez", "price": 2.65}, {"name": "Guadalajara", "price": 2.9}, {"name": "Draw", "price": 3.05}]}]}, {"key": "lowvig", "title": "LowVig.ag", "last_update": "2023-08-15T19:24:43Z", "markets": [{"key": "h2h", "last_update": "2023-08-15T19:24:43Z", "outcomes": [{"name": "FC Ju\u00e1rez", "price": 2.65}, {"name": "Guadalajara", "price": 2.9}, {"name": "Draw", "price": 3.05}]}]}]}, {"id": "48c84707a876f051e17b34c2a4f09e27", "sport_key": "soccer_mexico_ligamx", "sport_title": "Liga MX", "commence_time": "2023-08-19T20:00:00Z", "home_team": "Cruz Azul", "away_team": "Santos Laguna", "bookmakers": [{"key": "betrivers", "title": "BetRivers", "last_update": "2023-08-15T19:24:10Z", "markets": [{"key": "h2h", "last_update": "2023-08-15T19:24:10Z", "outcomes": [{"name": "Cruz Azul", "price": 2.32}, {"name": "Santos Laguna", "price": 3.0}, {"name": "Draw", "price": 3.25}]}]}, {"key": "twinspires", "title": "TwinSpires", "last_update": "2023-08-15T19:24:44Z", "markets": [{"key": "h2h", "last_update": "2023-08-15T19:24:44Z", "outcomes": [{"name": "Cruz Azul", "price": 2.32}, {"name": "Santos Laguna", "price": 3.0}, {"name": "Draw", "price": 3.25}]}]}, {"key": "betparx", "title": "betPARX", "last_update": "2023-08-15T19:25:11Z", "markets": [{"key": "h2h", "last_update": "2023-08-15T19:25:11Z", "outcomes": [{"name": "Cruz Azul", "price": 2.32}, {"name": "Santos Laguna", "price": 3.0}, {"name": "Draw", "price": 3.25}]}]}, {"key": "unibet_us", "title": "Unibet", "last_update": "2023-08-15T19:23:51Z", "markets": [{"key": "h2h", "last_update": "2023-08-15T19:23:51Z", "outcomes": [{"name": "Cruz Azul", "price": 2.32}, {"name": "Santos Laguna", "price": 3.0}, {"name": "Draw", "price": 3.25}]}]}]}, {"id": "49a21744502b01ee686699eec6011f90", "sport_key": "soccer_mexico_ligamx", "sport_title": "Liga MX", "commence_time": "2023-08-19T20:00:00Z", "home_team": "Necaxa", "away_team": "Tigres", "bookmakers": [{"key": "betrivers", "title": "BetRivers", "last_update": "2023-08-15T19:24:10Z", "markets": [{"key": "h2h", "last_update": "2023-08-15T19:24:10Z", "outcomes": [{"name": "Necaxa", "price": 3.3}, {"name": "Tigres", "price": 2.08}, {"name": "Draw", "price": 3.4}]}]}, {"key": "twinspires", "title": "TwinSpires", "last_update": "2023-08-15T19:24:44Z", "markets": [{"key": "h2h", "last_update": "2023-08-15T19:24:44Z", "outcomes": [{"name": "Necaxa", "price": 3.3}, {"name": "Tigres", "price": 2.08}, {"name": "Draw", "price": 3.4}]}]}, {"key": "betparx", "title": "betPARX", "last_update": "2023-08-15T19:25:11Z", "markets": [{"key": "h2h", "last_update": "2023-08-15T19:25:11Z", "outcomes": [{"name": "Necaxa", "price": 3.3}, {"name": "Tigres", "price": 2.08}, {"name": "Draw", "price": 3.4}]}]}, {"key": "unibet_us", "title": "Unibet", "last_update": "2023-08-15T19:23:51Z", "markets": [{"key": "h2h", "last_update": "2023-08-15T19:23:51Z", "outcomes": [{"name": "Necaxa", "price": 3.3}, {"name": "Tigres", "price": 2.08}, {"name": "Draw", "price": 3.4}]}]}]}, {"id": "0786f2dad4b5639e0b78b2730bc95400", "sport_key": "soccer_mexico_ligamx", "sport_title": "Liga MX", "commence_time": "2023-08-21T01:06:00Z", "home_team": "Quer\u00e9taro", "away_team": "Pachuca", "bookmakers": [{"key": "betrivers", "title": "BetRivers", "last_update": "2023-08-15T19:24:10Z", "markets": [{"key": "h2h", "last_update": "2023-08-15T19:24:10Z", "outcomes": [{"name": "Pachuca", "price": 2.38}, {"name": "Quer\u00e9taro", "price": 2.7}, {"name": "Draw", "price": 3.5}]}]}, {"key": "superbook", "title": "SuperBook", "last_update": "2023-08-15T19:23:51Z", "markets": [{"key": "h2h", "last_update": "2023-08-15T19:23:51Z", "outcomes": [{"name": "Pachuca", "price": 2.4}, {"name": "Quer\u00e9taro", "price": 2.8}, {"name": "Draw", "price": 3.35}]}]}, {"key": "twinspires", "title": "TwinSpires", "last_update": "2023-08-15T19:24:44Z", "markets": [{"key": "h2h", "last_update": "2023-08-15T19:24:44Z", "outcomes": [{"name": "Pachuca", "price": 2.38}, {"name": "Quer\u00e9taro", "price": 2.7}, {"name": "Draw", "price": 3.5}]}]}, {"key": "betparx", "title": "betPARX", "last_update": "2023-08-15T19:25:11Z", "markets": [{"key": "h2h", "last_update": "2023-08-15T19:25:11Z", "outcomes": [{"name": "Pachuca", "price": 2.38}, {"name": "Quer\u00e9taro", "price": 2.7}, {"name": "Draw", "price": 3.5}]}]}, {"key": "tipico_us", "title": "Tipico", "last_update": "2023-08-15T19:24:44Z", "markets": [{"key": "h2h", "last_update": "2023-08-15T19:24:44Z", "outcomes": [{"name": "Pachuca", "price": 2.35}, {"name": "Quer\u00e9taro", "price": 2.85}, {"name": "Draw", "price": 3.4}]}]}, {"key": "unibet_us", "title": "Unibet", "last_update": "2023-08-15T19:23:51Z", "markets": [{"key": "h2h", "last_update": "2023-08-15T19:23:51Z", "outcomes": [{"name": "Pachuca", "price": 2.38}, {"name": "Quer\u00e9taro", "price": 2.7}, {"name": "Draw", "price": 3.5}]}]}, {"key": "barstool", "title": "Barstool Sportsbook", "last_update": "2023-08-15T19:23:51Z", "markets": [{"key": "h2h", "last_update": "2023-08-15T19:23:51Z", "outcomes": [{"name": "Pachuca", "price": 2.37}, {"name": "Quer\u00e9taro", "price": 2.85}, {"name": "Draw", "price": 3.35}]}]}, {"key": "fanduel", "title": "FanDuel", "last_update": "2023-08-15T19:25:11Z", "markets": [{"key": "h2h", "last_update": "2023-08-15T19:25:11Z", "outcomes": [{"name": "Pachuca", "price": 2.4}, {"name": "Quer\u00e9taro", "price": 2.75}, {"name": "Draw", "price": 3.5}]}]}, {"key": "draftkings", "title": "DraftKings", "last_update": "2023-08-15T19:23:45Z", "markets": [{"key": "h2h", "last_update": "2023-08-15T19:23:45Z", "outcomes": [{"name": "Pachuca", "price": 2.35}, {"name": "Quer\u00e9taro", "price": 2.75}, {"name": "Draw", "price": 3.6}]}]}]}, {"id": "a0be87464aa9110282a64bb89880d942", "sport_key": "soccer_mexico_ligamx", "sport_title": "Liga MX", "commence_time": "2023-08-21T01:10:00Z", "home_team": "Atlas", "away_team": "Am\u00e9rica", "bookmakers": [{"key": "tipico_us", "title": "Tipico", "last_update": "2023-08-15T19:24:44Z", "markets": [{"key": "h2h", "last_update": "2023-08-15T19:24:44Z", "outcomes": [{"name": "Am\u00e9rica", "price": 2.33}, {"name": "Atlas", "price": 2.9}, {"name": "Draw", "price": 3.4}]}]}, {"key": "williamhill_us", "title": "William Hill (US)", "last_update": "2023-08-15T19:23:12Z", "markets": [{"key": "h2h", "last_update": "2023-08-15T19:23:12Z", "outcomes": [{"name": "Am\u00e9rica", "price": 2.3}, {"name": "Atlas", "price": 2.95}, {"name": "Draw", "price": 3.45}]}]}, {"key": "twinspires", "title": "TwinSpires", "last_update": "2023-08-15T19:24:44Z", "markets": [{"key": "h2h", "last_update": "2023-08-15T19:24:44Z", "outcomes": [{"name": "Am\u00e9rica", "price": 2.33}, {"name": "Atlas", "price": 2.9}, {"name": "Draw", "price": 3.35}]}]}, {"key": "betrivers", "title": "BetRivers", "last_update": "2023-08-15T19:24:10Z", "markets": [{"key": "h2h", "last_update": "2023-08-15T19:24:10Z", "outcomes": [{"name": "Am\u00e9rica", "price": 2.33}, {"name": "Atlas", "price": 2.9}, {"name": "Draw", "price": 3.35}]}]}, {"key": "superbook", "title": "SuperBook", "last_update": "2023-08-15T19:23:51Z", "markets": [{"key": "h2h", "last_update": "2023-08-15T19:23:51Z", "outcomes": [{"name": "Am\u00e9rica", "price": 2.35}, {"name": "Atlas", "price": 2.85}, {"name": "Draw", "price": 3.35}]}]}, {"key": "unibet_us", "title": "Unibet", "last_update": "2023-08-15T19:23:51Z", "markets": [{"key": "h2h", "last_update": "2023-08-15T19:23:51Z", "outcomes": [{"name": "Am\u00e9rica", "price": 2.33}, {"name": "Atlas", "price": 2.9}, {"name": "Draw", "price": 3.35}]}]}, {"key": "betparx", "title": "betPARX", "last_update": "2023-08-15T19:25:11Z", "markets": [{"key": "h2h", "last_update": "2023-08-15T19:25:11Z", "outcomes": [{"name": "Am\u00e9rica", "price": 2.33}, {"name": "Atlas", "price": 2.9}, {"name": "Draw", "price": 3.35}]}]}, {"key": "draftkings", "title": "DraftKings", "last_update": "2023-08-15T19:23:45Z", "markets": [{"key": "h2h", "last_update": "2023-08-15T19:23:45Z", "outcomes": [{"name": "Am\u00e9rica", "price": 2.3}, {"name": "Atlas", "price": 2.9}, {"name": "Draw", "price": 3.35}]}]}, {"key": "barstool", "title": "Barstool Sportsbook", "last_update": "2023-08-15T19:23:51Z", "markets": [{"key": "h2h", "last_update": "2023-08-15T19:23:51Z", "outcomes": [{"name": "Am\u00e9rica", "price": 2.32}, {"name": "Atlas", "price": 2.88}, {"name": "Draw", "price": 3.4}]}]}, {"key": "fanduel", "title": "FanDuel", "last_update": "2023-08-15T19:25:11Z", "markets": [{"key": "h2h", "last_update": "2023-08-15T19:25:11Z", "outcomes": [{"name": "Am\u00e9rica", "price": 2.3}, {"name": "Atlas", "price": 2.9}, {"name": "Draw", "price": 3.4}]}]}, {"key": "betonlineag", "title": "BetOnline.ag", "last_update": "2023-08-15T19:23:51Z", "markets": [{"key": "h2h", "last_update": "2023-08-15T19:23:51Z", "outcomes": [{"name": "Am\u00e9rica", "price": 2.3}, {"name": "Atlas", "price": 3.1}, {"name": "Draw", "price": 3.42}]}]}, {"key": "lowvig", "title": "LowVig.ag", "last_update": "2023-08-15T19:24:43Z", "markets": [{"key": "h2h", "last_update": "2023-08-15T19:24:43Z", "outcomes": [{"name": "Am\u00e9rica", "price": 2.3}, {"name": "Atlas", "price": 3.1}, {"name": "Draw", "price": 3.42}]}]}]}]