[{"id": "a9461258d18c50ca664c8b4b7355b656", "sport_key": "soccer_italy_serie_a", "sport_title": "Serie A - Italy", "commence_time": "2023-06-04T19:02:24Z", "home_team": "Lecce", "away_team": "Bologna", "bookmakers": [{"key": "fanduel", "title": "FanDuel", "last_update": "2023-06-04T20:45:39Z", "markets": [{"key": "h2h", "last_update": "2023-06-04T20:45:39Z", "outcomes": [{"name": "Bologna", "price": 1.24}, {"name": "Lecce", "price": 27.0}, {"name": "Draw", "price": 4.6}]}]}, {"key": "draftkings", "title": "DraftKings", "last_update": "2023-06-04T20:44:28Z", "markets": [{"key": "h2h", "last_update": "2023-06-04T20:44:28Z", "outcomes": [{"name": "Bologna", "price": 6.0}, {"name": "Lecce", "price": 4.5}, {"name": "Draw", "price": 1.48}]}]}, {"key": "bovada", "title": "Bovada", "last_update": "2023-06-04T20:45:39Z", "markets": [{"key": "h2h", "last_update": "2023-06-04T20:45:39Z", "outcomes": [{"name": "Bologna", "price": 1.26}, {"name": "Lecce", "price": 17.0}, {"name": "Draw", "price": 4.2}]}]}, {"key": "tipico_us", "title": "Tipico", "last_update": "2023-06-04T20:45:35Z", "markets": [{"key": "h2h", "last_update": "2023-06-04T20:45:35Z", "outcomes": [{"name": "Bologna", "price": 1.25}, {"name": "Lecce", "price": 27.0}, {"name": "Draw", "price": 4.65}]}]}, {"key": "mybookieag", "title": "MyBookie.ag", "last_update": "2023-06-04T20:45:32Z", "markets": [{"key": "h2h", "last_update": "2023-06-04T20:45:32Z", "outcomes": [{"name": "Bologna", "price": 3.95}, {"name": "Lecce", "price": 3.1}, {"name": "Draw", "price": 2.0}]}]}, {"key": "williamhill_us", "title": "William Hill (US)", "last_update": "2023-06-04T20:44:26Z", "markets": [{"key": "h2h", "last_update": "2023-06-04T20:44:26Z", "outcomes": [{"name": "Bologna", "price": 5.1}, {"name": "Lecce", "price": 4.1}, {"name": "Draw", "price": 1.61}]}]}, {"key": "pointsbetus", "title": "PointsBet (US)", "last_update": "2023-06-04T20:45:47Z", "markets": [{"key": "h2h", "last_update": "2023-06-04T20:45:47Z", "outcomes": [{"name": "Bologna", "price": 1.25}, {"name": "Lecce", "price": 23.0}, {"name": "Draw", "price": 4.5}]}]}, {"key": "foxbet", "title": "FOX Bet", "last_update": "2023-06-04T20:44:42Z", "markets": [{"key": "h2h", "last_update": "2023-06-04T20:44:42Z", "outcomes": [{"name": "Bologna", "price": 4.4}, {"name": "Lecce", "price": 3.3}, {"name": "Draw", "price": 1.8}]}]}]}, {"id": "9306230be3bc8d7df8626ef55dc170de", "sport_key": "soccer_italy_serie_a", "sport_title": "Serie A - Italy", "commence_time": "2023-06-04T19:02:25Z", "home_team": "AC Milan", "away_team": "Hellas Verona FC", "bookmakers": [{"key": "draftkings", "title": "DraftKings", "last_update": "2023-06-04T20:44:28Z", "markets": [{"key": "h2h", "last_update": "2023-06-04T20:44:28Z", "outcomes": [{"name": "AC Milan", "price": 3.25}, {"name": "Hellas Verona FC", "price": 7.5}, {"name": "Draw", "price": 1.61}]}]}, {"key": "fanduel", "title": "FanDuel", "last_update": "2023-06-04T20:45:39Z", "markets": [{"key": "h2h", "last_update": "2023-06-04T20:45:39Z", "outcomes": [{"name": "AC Milan", "price": 3.3}, {"name": "Hellas Verona FC", "price": 8.0}, {"name": "Draw", "price": 1.53}]}]}, {"key": "bovada", "title": "Bovada", "last_update": "2023-06-04T20:45:39Z", "markets": [{"key": "h2h", "last_update": "2023-06-04T20:45:39Z", "outcomes": [{"name": "AC Milan", "price": 3.05}, {"name": "Hellas Verona FC", "price": 8.0}, {"name": "Draw", "price": 1.56}]}]}, {"key": "mybookieag", "title": "MyBookie.ag", "last_update": "2023-06-04T20:45:32Z", "markets": [{"key": "h2h", "last_update": "2023-06-04T20:45:32Z", "outcomes": [{"name": "AC Milan", "price": 1.14}, {"name": "Hellas Verona FC", "price": 31.0}, {"name": "Draw", "price": 5.9}]}]}, {"key": "tipico_us", "title": "Tipico", "last_update": "2023-06-04T20:45:35Z", "markets": [{"key": "h2h", "last_update": "2023-06-04T20:45:35Z", "outcomes": [{"name": "AC Milan", "price": 3.25}, {"name": "Hellas Verona FC", "price": 9.25}, {"name": "Draw", "price": 1.57}]}]}, {"key": "williamhill_us", "title": "William Hill (US)", "last_update": "2023-06-04T20:45:08Z", "markets": [{"key": "h2h", "last_update": "2023-06-04T20:45:08Z", "outcomes": [{"name": "AC Milan", "price": 3.05}, {"name": "Hellas Verona FC", "price": 8.5}, {"name": "Draw", "price": 1.61}]}]}, {"key": "pointsbetus", "title": "PointsBet (US)", "last_update": "2023-06-04T20:45:47Z", "markets": [{"key": "h2h", "last_update": "2023-06-04T20:45:47Z", "outcomes": [{"name": "AC Milan", "price": 3.3}, {"name": "Hellas Verona FC", "price": 7.5}, {"name": "Draw", "price": 1.56}]}]}, {"key": "foxbet", "title": "FOX Bet", "last_update": "2023-06-04T20:45:24Z", "markets": [{"key": "h2h", "last_update": "2023-06-04T20:45:24Z", "outcomes": [{"name": "AC Milan", "price": 3.05}, {"name": "Hellas Verona FC", "price": 7.5}, {"name": "Draw", "price": 1.6}]}]}, {"key": "betmgm", "title": "BetMGM", "last_update": "2023-06-04T20:45:21Z", "markets": [{"key": "h2h", "last_update": "2023-06-04T20:45:21Z", "outcomes": [{"name": "AC Milan", "price": 3.1}, {"name": "Hellas Verona FC", "price": 7.75}, {"name": "Draw", "price": 1.57}]}]}]}, {"id": "1eaea33beafc307a85ffea943c5e0973", "sport_key": "soccer_italy_serie_a", "sport_title": "Serie A - Italy", "commence_time": "2023-06-04T19:02:26Z", "home_team": "Atalanta BC", "away_team": "Monza", "bookmakers": [{"key": "fanduel", "title": "FanDuel", "last_update": "2023-06-04T20:37:20Z", "markets": [{"key": "h2h", "last_update": "2023-06-04T20:37:20Z", "outcomes": [{"name": "Atalanta BC", "price": 1.05}, {"name": "Monza", "price": 171.0}, {"name": "Draw", "price": 12.0}]}]}, {"key": "draftkings", "title": "DraftKings", "last_update": "2023-06-04T20:36:53Z", "markets": [{"key": "h2h", "last_update": "2023-06-04T20:36:53Z", "outcomes": [{"name": "Atalanta BC", "price": 1.06}, {"name": "Monza", "price": 41.0}, {"name": "Draw", "price": 11.0}]}]}, {"key": "bovada", "title": "Bovada", "last_update": "2023-06-04T20:45:39Z", "markets": [{"key": "h2h", "last_update": "2023-06-04T20:45:39Z", "outcomes": [{"name": "Atalanta BC", "price": 1.06}, {"name": "Monza", "price": 81.0}, {"name": "Draw", "price": 9.25}]}]}, {"key": "mybookieag", "title": "MyBookie.ag", "last_update": "2023-06-04T20:45:32Z", "markets": [{"key": "h2h", "last_update": "2023-06-04T20:45:32Z", "outcomes": [{"name": "Atalanta BC", "price": 1.14}, {"name": "Monza", "price": 29.0}, {"name": "Draw", "price": 5.9}]}]}, {"key": "tipico_us", "title": "Tipico", "last_update": "2023-06-04T20:45:35Z", "markets": [{"key": "h2h", "last_update": "2023-06-04T20:45:35Z", "outcomes": [{"name": "Atalanta BC", "price": 1.07}, {"name": "Monza", "price": 50.0}, {"name": "Draw", "price": 21.0}]}]}, {"key": "williamhill_us", "title": "William Hill (US)", "last_update": "2023-06-04T20:45:08Z", "markets": [{"key": "h2h", "last_update": "2023-06-04T20:45:08Z", "outcomes": [{"name": "Atalanta BC", "price": 1.0}, {"name": "Monza", "price": 31.0}, {"name": "Draw", "price": 29.0}]}]}, {"key": "pointsbetus", "title": "PointsBet (US)", "last_update": "2023-06-04T20:45:47Z", "markets": [{"key": "h2h", "last_update": "2023-06-04T20:45:47Z", "outcomes": [{"name": "Atalanta BC", "price": 1.0}, {"name": "Monza", "price": 1001.0}, {"name": "Draw", "price": 101.0}]}]}, {"key": "foxbet", "title": "FOX Bet", "last_update": "2023-06-04T20:45:24Z", "markets": [{"key": "h2h", "last_update": "2023-06-04T20:45:24Z", "outcomes": [{"name": "Atalanta BC", "price": 1.0}, {"name": "Monza", "price": 251.0}, {"name": "Draw", "price": 34.0}]}]}]}, {"id": "2288421273bdcfde5b62bcd13b4be48e", "sport_key": "soccer_italy_serie_a", "sport_title": "Serie A - Italy", "commence_time": "2023-06-04T19:02:28Z", "home_team": "Udinese", "away_team": "Juventus", "bookmakers": [{"key": "fanduel", "title": "FanDuel", "last_update": "2023-06-04T20:45:39Z", "markets": [{"key": "h2h", "last_update": "2023-06-04T20:45:39Z", "outcomes": [{"name": "Juventus", "price": 1.12}, {"name": "Udinese", "price": 51.0}, {"name": "Draw", "price": 6.5}]}]}, {"key": "draftkings", "title": "DraftKings", "last_update": "2023-06-04T20:44:28Z", "markets": [{"key": "h2h", "last_update": "2023-06-04T20:44:28Z", "outcomes": [{"name": "Juventus", "price": 1.1}, {"name": "Udinese", "price": 36.0}, {"name": "Draw", "price": 8.0}]}]}, {"key": "bovada", "title": "Bovada", "last_update": "2023-06-04T20:45:39Z", "markets": [{"key": "h2h", "last_update": "2023-06-04T20:45:39Z", "outcomes": [{"name": "Juventus", "price": 1.1}, {"name": "Udinese", "price": 56.0}, {"name": "Draw", "price": 6.75}]}]}, {"key": "tipico_us", "title": "Tipico", "last_update": "2023-06-04T20:45:35Z", "markets": [{"key": "h2h", "last_update": "2023-06-04T20:45:35Z", "outcomes": [{"name": "Juventus", "price": 1.1}, {"name": "Udinese", "price": 50.0}, {"name": "Draw", "price": 7.5}]}]}, {"key": "mybookieag", "title": "MyBookie.ag", "last_update": "2023-06-04T20:45:32Z", "markets": [{"key": "h2h", "last_update": "2023-06-04T20:45:32Z", "outcomes": [{"name": "Juventus", "price": 2.1}, {"name": "Udinese", "price": 6.0}, {"name": "Draw", "price": 2.25}]}]}, {"key": "williamhill_us", "title": "William Hill (US)", "last_update": "2023-06-04T20:45:08Z", "markets": [{"key": "h2h", "last_update": "2023-06-04T20:45:08Z", "outcomes": [{"name": "Juventus", "price": 1.12}, {"name": "Udinese", "price": 51.0}, {"name": "Draw", "price": 6.75}]}]}, {"key": "pointsbetus", "title": "PointsBet (US)", "last_update": "2023-06-04T20:45:47Z", "markets": [{"key": "h2h", "last_update": "2023-06-04T20:45:47Z", "outcomes": [{"name": "Juventus", "price": 1.11}, {"name": "Udinese", "price": 41.0}, {"name": "Draw", "price": 6.0}]}]}, {"key": "foxbet", "title": "FOX Bet", "last_update": "2023-06-04T20:45:24Z", "markets": [{"key": "h2h", "last_update": "2023-06-04T20:45:24Z", "outcomes": [{"name": "Juventus", "price": 1.14}, {"name": "Udinese", "price": 29.0}, {"name": "Draw", "price": 5.75}]}]}, {"key": "betmgm", "title": "BetMGM", "last_update": "2023-06-04T20:45:21Z", "markets": [{"key": "h2h", "last_update": "2023-06-04T20:45:21Z", "outcomes": [{"name": "Juventus", "price": 1.11}, {"name": "Udinese", "price": 46.0}, {"name": "Draw", "price": 7.25}]}]}]}, {"id": "6662b1887b26917374c0c7d421a45d62", "sport_key": "soccer_italy_serie_a", "sport_title": "Serie A - Italy", "commence_time": "2023-06-04T19:02:34Z", "home_team": "AS Roma", "away_team": "Spezia", "bookmakers": [{"key": "fanduel", "title": "FanDuel", "last_update": "2023-06-04T20:45:39Z", "markets": [{"key": "h2h", "last_update": "2023-06-04T20:45:39Z", "outcomes": [{"name": "AS Roma", "price": 2.75}, {"name": "Spezia", "price": 9.0}, {"name": "Draw", "price": 1.62}]}]}, {"key": "draftkings", "title": "DraftKings", "last_update": "2023-06-04T20:43:06Z", "markets": [{"key": "h2h", "last_update": "2023-06-04T20:43:06Z", "outcomes": [{"name": "AS Roma", "price": 2.75}, {"name": "Spezia", "price": 8.5}, {"name": "Draw", "price": 1.71}]}]}, {"key": "bovada", "title": "Bovada", "last_update": "2023-06-04T20:45:39Z", "markets": [{"key": "h2h", "last_update": "2023-06-04T20:45:39Z", "outcomes": [{"name": "AS Roma", "price": 2.54}, {"name": "Spezia", "price": 7.0}, {"name": "Draw", "price": 1.77}]}]}, {"key": "mybookieag", "title": "MyBookie.ag", "last_update": "2023-06-04T20:45:32Z", "markets": [{"key": "h2h", "last_update": "2023-06-04T20:45:32Z", "outcomes": [{"name": "AS Roma", "price": 2.2}, {"name": "Spezia", "price": 7.0}, {"name": "Draw", "price": 2.05}]}]}, {"key": "tipico_us", "title": "Tipico", "last_update": "2023-06-04T20:45:35Z", "markets": [{"key": "h2h", "last_update": "2023-06-04T20:45:35Z", "outcomes": [{"name": "AS Roma", "price": 2.65}, {"name": "Spezia", "price": 8.0}, {"name": "Draw", "price": 1.8}]}]}, {"key": "williamhill_us", "title": "William Hill (US)", "last_update": "2023-06-04T20:45:08Z", "markets": [{"key": "h2h", "last_update": "2023-06-04T20:45:08Z", "outcomes": [{"name": "AS Roma", "price": 2.55}, {"name": "Spezia", "price": 7.5}, {"name": "Draw", "price": 1.84}]}]}, {"key": "pointsbetus", "title": "PointsBet (US)", "last_update": "2023-06-04T20:45:47Z", "markets": [{"key": "h2h", "last_update": "2023-06-04T20:45:47Z", "outcomes": [{"name": "AS Roma", "price": 2.65}, {"name": "Spezia", "price": 8.5}, {"name": "Draw", "price": 1.77}]}]}, {"key": "foxbet", "title": "FOX Bet", "last_update": "2023-06-04T20:45:24Z", "markets": [{"key": "h2h", "last_update": "2023-06-04T20:45:24Z", "outcomes": [{"name": "AS Roma", "price": 2.4}, {"name": "Spezia", "price": 8.5}, {"name": "Draw", "price": 1.8}]}]}, {"key": "betmgm", "title": "BetMGM", "last_update": "2023-06-04T20:45:21Z", "markets": [{"key": "h2h", "last_update": "2023-06-04T20:45:21Z", "outcomes": [{"name": "AS Roma", "price": 2.75}, {"name": "Spezia", "price": 8.25}, {"name": "Draw", "price": 1.67}]}]}]}]