[{"id": "a3384f2a8d735cd48020c5b5d269811a", "sport_key": "soccer_finland_veikkausliiga", "sport_title": "Veikkausliiga - Finland", "commence_time": "2023-07-01T11:00:00Z", "home_team": "FC Honka Espoo", "away_team": "HJK Helsinki", "bookmakers": [{"key": "bovada", "title": "Bovada", "last_update": "2023-06-28T22:53:19Z", "markets": [{"key": "h2h", "last_update": "2023-06-28T22:53:19Z", "outcomes": [{"name": "FC Honka Espoo", "price": 3.4}, {"name": "HJK Helsinki", "price": 2.2}, {"name": "Draw", "price": 3.0}]}]}, {"key": "williamhill_us", "title": "William Hill (US)", "last_update": "2023-06-28T22:52:25Z", "markets": [{"key": "h2h", "last_update": "2023-06-28T22:52:25Z", "outcomes": [{"name": "FC Honka Espoo", "price": 3.45}, {"name": "HJK Helsinki", "price": 2.08}, {"name": "Draw", "price": 2.95}]}]}, {"key": "mybookieag", "title": "MyBookie.ag", "last_update": "2023-06-28T22:52:26Z", "markets": [{"key": "h2h", "last_update": "2023-06-28T22:52:26Z", "outcomes": [{"name": "FC Honka Espoo", "price": 3.5}, {"name": "HJK Helsinki", "price": 2.19}, {"name": "Draw", "price": 3.15}]}]}, {"key": "betus", "title": "BetUS", "last_update": "2023-06-28T22:53:04Z", "markets": [{"key": "h2h", "last_update": "2023-06-28T22:53:04Z", "outcomes": [{"name": "FC Honka Espoo", "price": 3.55}, {"name": "HJK Helsinki", "price": 2.15}, {"name": "Draw", "price": 3.1}]}]}]}, {"id": "12d46526a90e84f0b81a65c84bc43e8c", "sport_key": "soccer_finland_veikkausliiga", "sport_title": "Veikkausliiga - Finland", "commence_time": "2023-07-01T14:00:00Z", "home_team": "AC Oulu", "away_team": "FC Haka", "bookmakers": [{"key": "bovada", "title": "Bovada", "last_update": "2023-06-28T22:53:19Z", "markets": [{"key": "h2h", "last_update": "2023-06-28T22:53:19Z", "outcomes": [{"name": "AC Oulu", "price": 2.2}, {"name": "FC Haka", "price": 3.25}, {"name": "Draw", "price": 3.15}]}]}, {"key": "williamhill_us", "title": "William Hill (US)", "last_update": "2023-06-28T22:52:25Z", "markets": [{"key": "h2h", "last_update": "2023-06-28T22:52:25Z", "outcomes": [{"name": "AC Oulu", "price": 2.11}, {"name": "FC Haka", "price": 3.2}, {"name": "Draw", "price": 3.1}]}]}, {"key": "mybookieag", "title": "MyBookie.ag", "last_update": "2023-06-28T22:52:26Z", "markets": [{"key": "h2h", "last_update": "2023-06-28T22:52:26Z", "outcomes": [{"name": "AC Oulu", "price": 2.19}, {"name": "FC Haka", "price": 3.3}, {"name": "Draw", "price": 3.35}]}]}, {"key": "betus", "title": "BetUS", "last_update": "2023-06-28T22:53:04Z", "markets": [{"key": "h2h", "last_update": "2023-06-28T22:53:04Z", "outcomes": [{"name": "AC Oulu", "price": 2.1}, {"name": "FC Haka", "price": 3.45}, {"name": "Draw", "price": 3.3}]}]}]}, {"id": "b4351b4e387bf6fd498f12befc662b26", "sport_key": "soccer_finland_veikkausliiga", "sport_title": "Veikkausliiga - Finland", "commence_time": "2023-07-01T14:00:00Z", "home_team": "VPS Vaasa", "away_team": "FC Inter Turku", "bookmakers": [{"key": "mybookieag", "title": "MyBookie.ag", "last_update": "2023-06-28T22:52:26Z", "markets": [{"key": "h2h", "last_update": "2023-06-28T22:52:26Z", "outcomes": [{"name": "FC Inter Turku", "price": 2.33}, {"name": "VPS Vaasa", "price": 3.1}, {"name": "Draw", "price": 3.3}]}]}, {"key": "williamhill_us", "title": "William Hill (US)", "last_update": "2023-06-28T22:52:25Z", "markets": [{"key": "h2h", "last_update": "2023-06-28T22:52:25Z", "outcomes": [{"name": "FC Inter Turku", "price": 2.18}, {"name": "VPS Vaasa", "price": 3.05}, {"name": "Draw", "price": 3.15}]}]}, {"key": "bovada", "title": "Bovada", "last_update": "2023-06-28T22:53:19Z", "markets": [{"key": "h2h", "last_update": "2023-06-28T22:53:19Z", "outcomes": [{"name": "FC Inter Turku", "price": 2.35}, {"name": "VPS Vaasa", "price": 3.0}, {"name": "Draw", "price": 3.1}]}]}, {"key": "betus", "title": "BetUS", "last_update": "2023-06-28T22:53:04Z", "markets": [{"key": "h2h", "last_update": "2023-06-28T22:53:04Z", "outcomes": [{"name": "FC Inter Turku", "price": 2.25}, {"name": "VPS Vaasa", "price": 3.15}, {"name": "Draw", "price": 3.25}]}]}]}, {"id": "fa89b6731da3e4c013006231d6bb472c", "sport_key": "soccer_finland_veikkausliiga", "sport_title": "Veikkausliiga - Finland", "commence_time": "2023-07-01T14:00:00Z", "home_team": "Ilves Tampere", "away_team": "SJK Sein\u00e4joki", "bookmakers": [{"key": "williamhill_us", "title": "William Hill (US)", "last_update": "2023-06-28T22:52:25Z", "markets": [{"key": "h2h", "last_update": "2023-06-28T22:52:25Z", "outcomes": [{"name": "Ilves Tampere", "price": 2.7}, {"name": "SJK Sein\u00e4joki", "price": 2.5}, {"name": "Draw", "price": 2.95}]}]}, {"key": "mybookieag", "title": "MyBookie.ag", "last_update": "2023-06-28T22:52:26Z", "markets": [{"key": "h2h", "last_update": "2023-06-28T22:52:26Z", "outcomes": [{"name": "Ilves Tampere", "price": 2.8}, {"name": "SJK Sein\u00e4joki", "price": 2.6}, {"name": "Draw", "price": 3.15}]}]}, {"key": "bovada", "title": "Bovada", "last_update": "2023-06-28T22:53:19Z", "markets": [{"key": "h2h", "last_update": "2023-06-28T22:53:19Z", "outcomes": [{"name": "Ilves Tampere", "price": 2.7}, {"name": "SJK Sein\u00e4joki", "price": 2.55}, {"name": "Draw", "price": 3.15}]}]}, {"key": "betus", "title": "BetUS", "last_update": "2023-06-28T22:53:04Z", "markets": [{"key": "h2h", "last_update": "2023-06-28T22:53:04Z", "outcomes": [{"name": "Ilves Tampere", "price": 2.8}, {"name": "SJK Sein\u00e4joki", "price": 2.55}, {"name": "Draw", "price": 3.15}]}]}]}, {"id": "a06955ad2fa87d7359c875ea7a141b85", "sport_key": "soccer_finland_veikkausliiga", "sport_title": "Veikkausliiga - Finland", "commence_time": "2023-07-01T15:30:00Z", "home_team": "IFK Mariehamn", "away_team": "FC KTP", "bookmakers": [{"key": "williamhill_us", "title": "William Hill (US)", "last_update": "2023-06-28T22:52:25Z", "markets": [{"key": "h2h", "last_update": "2023-06-28T22:52:25Z", "outcomes": [{"name": "FC KTP", "price": 2.7}, {"name": "IFK Mariehamn", "price": 2.35}, {"name": "Draw", "price": 3.25}]}]}, {"key": "mybookieag", "title": "MyBookie.ag", "last_update": "2023-06-28T22:52:26Z", "markets": [{"key": "h2h", "last_update": "2023-06-28T22:52:26Z", "outcomes": [{"name": "FC KTP", "price": 2.9}, {"name": "IFK Mariehamn", "price": 2.38}, {"name": "Draw", "price": 3.4}]}]}, {"key": "bovada", "title": "Bovada", "last_update": "2023-06-28T22:53:19Z", "markets": [{"key": "h2h", "last_update": "2023-06-28T22:53:19Z", "outcomes": [{"name": "FC KTP", "price": 2.85}, {"name": "IFK Mariehamn", "price": 2.4}, {"name": "Draw", "price": 3.25}]}]}, {"key": "betus", "title": "BetUS", "last_update": "2023-06-28T22:53:04Z", "markets": [{"key": "h2h", "last_update": "2023-06-28T22:53:04Z", "outcomes": [{"name": "FC KTP", "price": 2.8}, {"name": "IFK Mariehamn", "price": 2.4}, {"name": "Draw", "price": 3.45}]}]}]}, {"id": "e2f7eeff379fdf238ebafa1690b53c2f", "sport_key": "soccer_finland_veikkausliiga", "sport_title": "Veikkausliiga - Finland", "commence_time": "2023-07-01T16:00:00Z", "home_team": "FC Lahti", "away_team": "KuPS Kuopio", "bookmakers": [{"key": "bovada", "title": "Bovada", "last_update": "2023-06-28T22:53:19Z", "markets": [{"key": "h2h", "last_update": "2023-06-28T22:53:19Z", "outcomes": [{"name": "FC Lahti", "price": 5.0}, {"name": "KuPS Kuopio", "price": 1.69}, {"name": "Draw", "price": 3.5}]}]}, {"key": "williamhill_us", "title": "William Hill (US)", "last_update": "2023-06-28T22:52:25Z", "markets": [{"key": "h2h", "last_update": "2023-06-28T22:52:25Z", "outcomes": [{"name": "FC Lahti", "price": 5.3}, {"name": "KuPS Kuopio", "price": 1.59}, {"name": "Draw", "price": 3.45}]}]}, {"key": "mybookieag", "title": "MyBookie.ag", "last_update": "2023-06-28T22:52:26Z", "markets": [{"key": "h2h", "last_update": "2023-06-28T22:52:26Z", "outcomes": [{"name": "FC Lahti", "price": 5.2}, {"name": "KuPS Kuopio", "price": 1.68}, {"name": "Draw", "price": 3.7}]}]}, {"key": "betus", "title": "BetUS", "last_update": "2023-06-28T22:53:04Z", "markets": [{"key": "h2h", "last_update": "2023-06-28T22:53:04Z", "outcomes": [{"name": "FC Lahti", "price": 5.3}, {"name": "KuPS Kuopio", "price": 1.62}, {"name": "Draw", "price": 3.65}]}]}]}, {"id": "2df6c986ac81bfe688e33b03df0e4d09", "sport_key": "soccer_finland_veikkausliiga", "sport_title": "Veikkausliiga - Finland", "commence_time": "2023-07-22T14:00:00Z", "home_team": "HJK Helsinki", "away_team": "Ilves Tampere", "bookmakers": []}]